{
    "seasons":
    {
        "languages":
        {
            "eng":
            [
                "winter",
                "spring",
                "summer",
                "autumn"
            ],
            "spa":
            [
                "invierno",
                "primavera",
                "verano",
                "otoño",
                "otono"
            ],
            "vie":
            [
                "mùađông",
                "muadong",
                "mùaxuân",
                "muaxuan",
                "mùahè",
                "mùahạ",
                "muahe",
                "muaha",
                "mùathu",
                "muathu"
            ],
            "por":
            [
                "inverno",
                "primavera",
                "verão",
                "verao",
                "outono"
            ],
            "cat":
            [
                "hivern",
                "primavera",
                "estiu",
                "tardor"
            ],
            "glg":
            [
                "inverno",
                "primavera",
                "verán",
                "veran",
                "outono"
            ]
        }
    }
}
